{"id": 3977, "uid": "7e5f0b8d-f4f0-42ab-9a0b-60a571912520", "word": "meggings", "words": ["health", "Thundercats", "mumblecore"], "sentence": "Single-origin coffee fixie cleanse blog.", "sentences": ["Echo truffaut photo booth.", "Shabby chic selfies chillwave green juice phlogiston.", "Wes anderson bushwick pickled slow-carb truffaut vhs normcore."], "paragraph": "3 wolf moon +1 cleanse. Blue bottle shabby chic muggle magic 3 wolf moon tattooed 90's twee. Echo poutine skateboard.", "paragraphs": ["Mixtape vegan lomo 3 wolf moon normcore scenester. Waistcoat hammock loko slow-carb meh. Blue bottle aesthetic 90's.", "Fingerstache selvage chillwave leggings. Viral lomo put a bird on it kogi. Tousled narwhal 3 wolf moon fashion axe cliche locavore poutine. Humblebrag plaid forage.", "Actually butcher plaid ugh farm-to-table. Loko kombucha fanny pack you probably haven't heard of them. Cleanse venmo wayfarers wes anderson bushwick stumptown fashion axe."]}