{"id": 6046, "uid": "ebdbba10-fd6a-4db8-b3ff-76ac0049c623", "word": "VHS", "words": ["stumptown", "hella", "goth"], "sentence": "Chia raw denim twee yolo shabby chic.", "sentences": ["Chia crucifix scenester hammock forage listicle vinegar.", "Letterpress polaroid next level you probably haven't heard of them drinking.", "Butcher wes anderson cronut church-key banjo yuccie whatever thundercats."], "paragraph": "Phlogiston green juice salvia you probably haven't heard of them five dollar toast ramps wes anderson. Loko park wolf. Tofu poutine wolf plaid phlogiston echo ennui banjo. Try-hard lomo organic. Vinegar fanny pack everyday hammock next level +1 pitchfork.", "paragraphs": ["Diy iphone knausgaard. Kale chips cray portland heirloom. Muggle magic cliche actually.", "Quinoa normcore park chillwave lumbersexual banjo venmo. Umami mumblecore plaid austin knausgaard biodiesel bitters. Knausgaard heirloom synth next level blog 90's put a bird on it.", "90's before they sold out tattooed. Hashtag chartreuse cornhole occupy selfies. Mustache etsy normcore pabst hammock."]}